brezn/__init__.py
brezn/config.py
brezn/files.py
brezn/main.py
brezn-0.1.0.dist-info/entry_points.txt
brezn-0.1.0.dist-info/LICENSE
brezn-0.1.0.dist-info/WHEEL
brezn-0.1.0.dist-info/METADATA
brezn-0.1.0.dist-info/RECORD
