Metadata-Version: 2.1
Name: brezn
Version: 0.1.0
Summary: Something layered on top of hydra.
Author-email: Marten Lienen <marten.lienen@gmail.com>
Requires-Python: >= 3.6
Classifier: Development Status :: 3 - Alpha
Classifier: Intended Audience :: Developers
Classifier: License :: OSI Approved :: MIT License
Classifier: Operating System :: OS Independent
Classifier: Programming Language :: Python
Requires-Dist: click
Requires-Dist: gitignorant
Requires-Dist: pytest ; extra == "test"
Project-URL: homepage, https://github.com/martenlienen/brezn
Provides-Extra: test
